MANIFEST.in
README.rst
setup.py
django_push2.egg-info/PKG-INFO
django_push2.egg-info/SOURCES.txt
django_push2.egg-info/dependency_links.txt
django_push2.egg-info/namespace_packages.txt
django_push2.egg-info/not-zip-safe
django_push2.egg-info/requires.txt
django_push2.egg-info/top_level.txt
push2/__init__.py
push2/admin.py
push2/connections.py
push2/models.py
push2/signals.py
push2/tests.py
push2/urls.py
push2/utils.py
push2/views.py
push2/static/push2/js/jsPush.js